{
	"info": {
		"name": "SpringREST",
		"_postman_id": "9570d523-7486-c426-0a3d-6fa6f217ca8d",
		"description": "Spring Boot REST Service",
		"schema": "https://schema.getpostman.com/json/collection/v2.1.0/collection.json"
	},
	"item": [
		{
			"name": "GET - All People",
			"request": {
				"method": "GET",
				"header": [],
				"body": {},
				"url": {
					"raw": "localhost:8080/people",
					"host": [
						"localhost"
					],
					"port": "8080",
					"path": [
						"people"
					]
				},
				"description": ""
			},
			"response": []
		},
		{
			"name": "GET - Specific Person By ID",
			"request": {
				"method": "GET",
				"header": [],
				"body": {},
				"url": {
					"raw": "localhost:8080/people/1",
					"host": [
						"localhost"
					],
					"port": "8080",
					"path": [
						"people",
						"1"
					]
				},
				"description": ""
			},
			"response": []
		},
		{
			"name": "POST - Add New Person",
			"request": {
				"method": "POST",
				"header": [
					{
						"key": "Content-Type",
						"value": "application/json"
					}
				],
				"body": {
					"mode": "raw",
					"raw": "{\n    \"name\": \"Person Two\",\n    \"city\": \"City-2\",\n    \"age\": 45,\n    \"occupation\": \"Occupation-2\",\n    \"annualTax\": 123.45\n}"
				},
				"url": {
					"raw": "localhost:8080/people/",
					"host": [
						"localhost"
					],
					"port": "8080",
					"path": [
						"people",
						""
					]
				},
				"description": ""
			},
			"response": []
		}
	]
}